citybrain/__init__.py
citybrain/api.py
src/__init__.py
src/api.py
src/citybrain.py
citybrain-0.0.4.dist-info/LICENSE.md
citybrain-0.0.4.dist-info/METADATA
citybrain-0.0.4.dist-info/WHEEL
citybrain-0.0.4.dist-info/top_level.txt
citybrain-0.0.4.dist-info/RECORD
