Metadata-Version: 2.1
Name: citybrain
Version: 0.0.4
Summary: make it easy to use data network of citybrain.org
Home-page: 
Author: citybrain.org
Author-email: allenlikeu@gmail.com
License: UNKNOWN
Platform: UNKNOWN
Classifier: Development Status :: 4 - Beta
Classifier: Programming Language :: Python :: 3
Classifier: License :: OSI Approved :: MIT License
Classifier: Operating System :: OS Independent
License-File: LICENSE.md
Requires-Dist: certifi (==2022.9.14)
Requires-Dist: charset-normalizer (==2.1.1)
Requires-Dist: idna (==3.4)
Requires-Dist: pandas (==1.5.0)
Requires-Dist: requests (==2.28.1)
Requires-Dist: urllib3 (==1.26.12)
